Metadata-Version: 1.1
Name: django-postgres-extra-kauffman
Version: 1.21a12
Summary: Bringing all of PostgreSQL's awesomeness to Django.
Home-page: https://github.com/zak10/django-postgres-extra
Author: Sector Labs
Author-email: open-source@sectorlabs.ro
License: MIT License
Keywords: django,postgres,extra,hstore,ltree
Platform: UNKNOWN
Classifier: Environment :: Web Environment
Classifier: Framework :: Django
Classifier: Intended Audience :: Developers
Classifier: License :: OSI Approved :: MIT License
Classifier: Operating System :: OS Independent
Classifier: Programming Language :: Python
Classifier: Programming Language :: Python :: 3.5
Classifier: Topic :: Internet :: WWW/HTTP
Classifier: Topic :: Internet :: WWW/HTTP :: Dynamic Content
